AUTHORS.md
CHANGES.md
LICENSE
MANIFEST.in
README.rst
setup.cfg
setup.py
kafka3/__init__.py
kafka3/client_async.py
kafka3/cluster.py
kafka3/codec.py
kafka3/conn.py
kafka3/errors.py
kafka3/future.py
kafka3/scram.py
kafka3/structs.py
kafka3/util.py
kafka3/version.py
kafka3/admin/__init__.py
kafka3/admin/acl_resource.py
kafka3/admin/client.py
kafka3/admin/config_resource.py
kafka3/admin/new_partitions.py
kafka3/admin/new_topic.py
kafka3/consumer/__init__.py
kafka3/consumer/fetcher.py
kafka3/consumer/group.py
kafka3/consumer/subscription_state.py
kafka3/coordinator/__init__.py
kafka3/coordinator/base.py
kafka3/coordinator/consumer.py
kafka3/coordinator/heartbeat.py
kafka3/coordinator/protocol.py
kafka3/coordinator/assignors/__init__.py
kafka3/coordinator/assignors/abstract.py
kafka3/coordinator/assignors/range.py
kafka3/coordinator/assignors/roundrobin.py
kafka3/coordinator/assignors/sticky/__init__.py
kafka3/coordinator/assignors/sticky/partition_movements.py
kafka3/coordinator/assignors/sticky/sorted_set.py
kafka3/coordinator/assignors/sticky/sticky_assignor.py
kafka3/metrics/__init__.py
kafka3/metrics/compound_stat.py
kafka3/metrics/dict_reporter.py
kafka3/metrics/kafka_metric.py
kafka3/metrics/measurable.py
kafka3/metrics/measurable_stat.py
kafka3/metrics/metric_config.py
kafka3/metrics/metric_name.py
kafka3/metrics/metrics.py
kafka3/metrics/metrics_reporter.py
kafka3/metrics/quota.py
kafka3/metrics/stat.py
kafka3/metrics/stats/__init__.py
kafka3/metrics/stats/avg.py
kafka3/metrics/stats/count.py
kafka3/metrics/stats/histogram.py
kafka3/metrics/stats/max_stat.py
kafka3/metrics/stats/min_stat.py
kafka3/metrics/stats/percentile.py
kafka3/metrics/stats/percentiles.py
kafka3/metrics/stats/rate.py
kafka3/metrics/stats/sampled_stat.py
kafka3/metrics/stats/sensor.py
kafka3/metrics/stats/total.py
kafka3/oauth/__init__.py
kafka3/oauth/abstract.py
kafka3/partitioner/__init__.py
kafka3/partitioner/default.py
kafka3/producer/__init__.py
kafka3/producer/buffer.py
kafka_python3.egg-info/PKG-INFO
kafka_python3.egg-info/SOURCES.txt
kafka_python3.egg-info/dependency_links.txt
kafka_python3.egg-info/requires.txt
kafka_python3.egg-info/top_level.txt
