Metadata-Version: 2.1
Name: kafka-python3
Version: 3.0.0
Summary: Pure Python client for Apache Kafka
Home-page: https://github.com/dpkp/kafka-python
Author: Dana Powers
Author-email: dana.powers@gmail.com
License: Apache License 2.0
Keywords: apache kafka
Platform: UNKNOWN
Classifier: Development Status :: 5 - Production/Stable
Classifier: Intended Audience :: Developers
Classifier: License :: OSI Approved :: Apache Software License
Classifier: Programming Language :: Python
Classifier: Programming Language :: Python :: 2
Classifier: Programming Language :: Python :: 2.7
Classifier: Programming Language :: Python :: 3
Classifier: Programming Language :: Python :: 3.4
Classifier: Programming Language :: Python :: 3.5
Classifier: Programming Language :: Python :: 3.6
Classifier: Programming Language :: Python :: 3.7
Classifier: Programming Language :: Python :: 3.8
Classifier: Programming Language :: Python :: Implementation :: PyPy
Classifier: Topic :: Software Development :: Libraries :: Python Modules
Provides-Extra: crc32c
Provides-Extra: lz4
Provides-Extra: snappy
Provides-Extra: zstd
